README
kloutpy.py
kloutpy_util.py
setup.py
kloutpy.egg-info/PKG-INFO
kloutpy.egg-info/SOURCES.txt
kloutpy.egg-info/dependency_links.txt
kloutpy.egg-info/top_level.txt