Metadata-Version: 1.1
Name: kloutpy
Version: 0.3
Summary: Python client for the klout api (http://klout.com/)
Home-page: https://github.com/rogeliorv/kloutpy/
Author: @rogeliorv
Author-email: UNKNOWN
License: LGPL3
Download-URL: https://github.com/rogeliorv/kloutpy/tarball/master
Keywords: klout
Platform: UNKNOWN
Classifier: Development Status :: 4 - Beta
Classifier: Topic :: Utilities
Classifier: License :: OSI Approved :: GNU Library or Lesser General Public License (LGPL)
Classifier: Natural Language :: English
Classifier: Operating System :: OS Independent
Classifier: Programming Language :: Python :: 2
Classifier: Topic :: Internet
Classifier: Topic :: Internet :: WWW/HTTP
